gcop/__init__.py
gcop/__main__.py
gcop/config.py
gcop/prompt.py
gcop/utils/__init__.py
gcop/utils/logger.py
gcop-1.7.3.dist-info/LICENSE
gcop-1.7.3.dist-info/METADATA
gcop-1.7.3.dist-info/WHEEL
gcop-1.7.3.dist-info/entry_points.txt
gcop-1.7.3.dist-info/RECORD
