Metadata-Version: 2.1
Name: gcop
Version: 1.7.3
Summary: gcop is your git AI copilot.
Home-page: https://github.com/Undertone0809/gcop
License: MIT
Keywords: gcop,git,git copilot,promptulate,pne,LLM,zeeland
Author: gcop
Author-email: zeeland4work@gmail.com
Requires-Python: >=3.8.1,<4.0
Classifier: License :: OSI Approved :: MIT License
Classifier: Programming Language :: Python :: 3
Classifier: Programming Language :: Python :: 3.9
Classifier: Programming Language :: Python :: 3.10
Classifier: Programming Language :: Python :: 3.11
Classifier: Programming Language :: Python :: 3.12
Requires-Dist: click (>=8.1.7,<9.0.0)
Requires-Dist: pne (>=1.1.1,<2.0.0)
Requires-Dist: pyyaml (>=6.0.1,<7.0.0)
Requires-Dist: questionary (>=2.0.1,<3.0.0)
Requires-Dist: rich (>=13.7.1,<14.0.0)
Requires-Dist: typer (>=0.12.3,<0.13.0)
Requires-Dist: zeeland (>=0.3.0,<1.0.0)
Project-URL: Repository, https://github.com/Undertone0809/gcop
